odoo/addons/sale_coupon_incompatibility/README.rst
odoo/addons/sale_coupon_incompatibility/__init__.py
odoo/addons/sale_coupon_incompatibility/__manifest__.py
odoo/addons/sale_coupon_incompatibility/i18n/sale_coupon_incompatibility.pot
odoo/addons/sale_coupon_incompatibility/models/__init__.py
odoo/addons/sale_coupon_incompatibility/models/sale_coupon.py
odoo/addons/sale_coupon_incompatibility/models/sale_coupon_program.py
odoo/addons/sale_coupon_incompatibility/readme/CONFIGURE.rst
odoo/addons/sale_coupon_incompatibility/readme/CONTRIBUTORS.rst
odoo/addons/sale_coupon_incompatibility/readme/DESCRIPTION.rst
odoo/addons/sale_coupon_incompatibility/readme/USAGE.rst
odoo/addons/sale_coupon_incompatibility/static/description/icon.png
odoo/addons/sale_coupon_incompatibility/static/description/icon.svg
odoo/addons/sale_coupon_incompatibility/static/description/index.html
odoo/addons/sale_coupon_incompatibility/tests/__init__.py
odoo/addons/sale_coupon_incompatibility/tests/test_sale_coupon_incompatibility.py
odoo/addons/sale_coupon_incompatibility/views/sale_coupon_program_views.xml
odoo13_addon_sale_coupon_incompatibility-13.0.1.0.1.dev3.dist-info/METADATA
odoo13_addon_sale_coupon_incompatibility-13.0.1.0.1.dev3.dist-info/WHEEL
odoo13_addon_sale_coupon_incompatibility-13.0.1.0.1.dev3.dist-info/top_level.txt
odoo13_addon_sale_coupon_incompatibility-13.0.1.0.1.dev3.dist-info/RECORD
